{"ongoing_trials": {"tuner0": "2"}, "hyperparameters": {"space": [{"class_name": "Int", "config": {"name": "units", "default": null, "conditions": [], "min_value": 32, "max_value": 192, "step": 8, "sampling": "linear"}}, {"class_name": "Choice", "config": {"name": "learning_rate", "default": 0.01, "conditions": [], "values": [0.01, 0.001, 0.0001], "ordered": true}}], "values": {"units": 32, "learning_rate": 0.01}}, "start_order": ["0", "1", "2"], "end_order": ["0", "1"], "run_times": {"0": 1, "1": 1}, "retry_queue": [], "seed": 1082, "seed_state": 1088, "tried_so_far": ["903857092282cd692dc8b1f9f2be2db0", "2af05038e3bbbeabdb0ae652ae4ac6bf", "f969dd65329c36f2e013a78e7c0d6e49"], "id_to_hash": {"0": "f969dd65329c36f2e013a78e7c0d6e49", "1": "2af05038e3bbbeabdb0ae652ae4ac6bf", "2": "903857092282cd692dc8b1f9f2be2db0"}}